llama_index/embeddings/together/__init__.py
llama_index/embeddings/together/base.py
llama_index_embeddings_together-0.4.1.dist-info/METADATA
llama_index_embeddings_together-0.4.1.dist-info/WHEEL
llama_index_embeddings_together-0.4.1.dist-info/licenses/LICENSE
llama_index_embeddings_together-0.4.1.dist-info/RECORD
